stabilizer_states/__init__.py
stabilizer_states/datasets/S1.npy
stabilizer_states/datasets/S2.npy
stabilizer_states/datasets/S3.npy
stabilizer_states/datasets/S4.npy
stabilizer_states/datasets/S5.npy
stabilizer_states/datasets/S5_ternary.npy
stabilizer_states/datasets/S6_ternary.npy
stabilizer_states/datasets/__init__.py
stabilizer_states/stabilizer_states.py
stabilizer_states-0.1.1.dist-info/LICENSE
stabilizer_states-0.1.1.dist-info/METADATA
stabilizer_states-0.1.1.dist-info/WHEEL
stabilizer_states-0.1.1.dist-info/RECORD
