Metadata-Version: 2.1
Name: stabilizer-states
Version: 0.1.1
Summary: A supporting (optional) library for stabilizer-toolkit that provides stabilizer states.
License: Apache-2.0
Author: Amir Ebrahimi
Author-email: github@aebrahimi.com
Requires-Python: >=3.9,<4.0
Classifier: License :: OSI Approved :: Apache Software License
Classifier: Programming Language :: Python :: 3
Classifier: Programming Language :: Python :: 3.9
Classifier: Programming Language :: Python :: 3.10
Classifier: Programming Language :: Python :: 3.11
Requires-Dist: numpy (>=1.23,<2.0)
